{
    "Overview": {
        "brand": "Coleman (active gear)",
        "values": {
            "Purpose": "79.4",
            "Emotional": "72.3",
            "Functional": "-",
            "Experiential": "-"
        }
    },
    "Purpose": {
        "brand": "Coleman (active gear)",
        "values": {
            "Universal Connection": "79.9",
            "Consistent Focus": "93.3",
            "Social Impact": "81.0",
            "Protagonism": "41.1"
        }
    },
    "Emotional": {
        "brand": "Coleman (active gear)",
        "values": {
            "Competence": "81.0",
            "Excitement": "57.8",
            "Ruggedness": "99.2",
            "Sincerity": "79.8",
            "Sophistication": "49.0"
        }
    }
}